jaxDiversity/__init__.py
jaxDiversity/_modidx.py
jaxDiversity/baseline.py
jaxDiversity/dataloading.py
jaxDiversity/hnn.py
jaxDiversity/loops.py
jaxDiversity/mlp.py
jaxDiversity/utilclasses.py
jaxDiversity-0.0.2.dist-info/LICENSE
jaxDiversity-0.0.2.dist-info/METADATA
jaxDiversity-0.0.2.dist-info/WHEEL
jaxDiversity-0.0.2.dist-info/entry_points.txt
jaxDiversity-0.0.2.dist-info/top_level.txt
jaxDiversity-0.0.2.dist-info/RECORD
