Metadata-Version: 2.1
Name: jaxDiversity
Version: 0.0.2
Summary: jax implementation for metalearning neuronal diversity
Home-page: https://github.com/NonlinearArtificialIntelligenceLab/jaxDiversity
Author: Anil Radhakrishnan
Author-email: aradhak5@ncsu.edu
License: Apache Software License 2.0
Keywords: nbdev jupyter notebook python
Classifier: Development Status :: 4 - Beta
Classifier: Intended Audience :: Developers
Classifier: Natural Language :: English
Classifier: Programming Language :: Python :: 3.9
Classifier: Programming Language :: Python :: 3.10
Classifier: License :: OSI Approved :: Apache Software License
Requires-Python: >=3.9
License-File: LICENSE
Requires-Dist: nbdev
Requires-Dist: jax
Requires-Dist: jaxlib
Requires-Dist: optax
Requires-Dist: equinox
Requires-Dist: fastcore
Requires-Dist: matplotlib
Requires-Dist: pandas
Requires-Dist: torch
Requires-Dist: seaborn
Requires-Dist: tqdm
Provides-Extra: dev
